catbridge/__init__.py
catbridge/catbridge.py
catbridge-1.0.dist-info/LICENSE
catbridge-1.0.dist-info/METADATA
catbridge-1.0.dist-info/WHEEL
catbridge-1.0.dist-info/top_level.txt
catbridge-1.0.dist-info/RECORD
