Metadata-Version: 2.1
Name: catbridge
Version: 1.0
Summary: CAT Bridge (Compounds And Transcripts Bridge) is a comprehensive longitudinal multi-omics analysis tool
Home-page: https://github.com/Bowen999/CAT-Bridge
Author: Bowen Yang
Author-email: by172@georgetown.edu
Classifier: License :: OSI Approved :: Python Software Foundation License
License-File: LICENSE
